licensematrix/__init__.py
licensematrix/dev/embarkStudios.rb
licensematrix/dev/license_matrix.json
licensematrix/dev/licenselist.txt
licensematrix/dev/notes.txt
licensematrix/dev/pypi_classifiers.json
licensematrix/dev/pypiclassifiers.txt
licensematrix/dev/spdx.json
licensematrix/dev/update_matrix.py
licensematrix/dev/update_pypiclassifiers.py
licensematrix/license_matrix.json
licensematrix/license_matrix.py
licensematrix/license_type.py
licensematrix/lm_schema.json
licensematrix-2024.dist-info/LICENSE.md
licensematrix-2024.dist-info/METADATA
licensematrix-2024.dist-info/WHEEL
licensematrix-2024.dist-info/RECORD
