Metadata-Version: 2.1
Name: licensematrix
Version: 2024
Summary: List of popular open source licenses with naive functions to determine compatibility and search for a license from a string
Home-page: https://github.com/FHPythonUtils/LicenseMatrix
License: MIT
Author: FredHappyface
Requires-Python: >=3.8,<4.0
Classifier: Development Status :: 5 - Production/Stable
Classifier: Environment :: Console
Classifier: Environment :: MacOS X
Classifier: Environment :: Win32 (MS Windows)
Classifier: Intended Audience :: Developers
Classifier: Intended Audience :: Education
Classifier: License :: OSI Approved :: MIT License
Classifier: Natural Language :: English
Classifier: Operating System :: OS Independent
Classifier: Programming Language :: Python :: 3
Classifier: Programming Language :: Python :: 3.8
Classifier: Programming Language :: Python :: 3.9
Classifier: Programming Language :: Python :: 3.10
Classifier: Programming Language :: Python :: 3.11
Classifier: Programming Language :: Python :: 3.12
Classifier: Programming Language :: Python :: Implementation :: CPython
Classifier: Topic :: Security
Classifier: Topic :: Software Development :: Libraries :: Python Modules
Classifier: Topic :: Utilities
Project-URL: Documentation, https://github.com/FHPythonUtils/LicenseMatrix/blob/master/README.md
Project-URL: Repository, https://github.com/FHPythonUtils/LicenseMatrix
